Metadata-Version: 1.0
Name: VanescoSC2
Version: 0.0.1
Summary: StarCraft II AI
Home-page: https://github.com/TheChyz/VanescoSC2
Author: TheChyz
Author-email: cmichal@hotmail.ca
License: MIT
Platform: UNKNOWN
